{
  "name": "fuerteventura",
  "largeHeading": "Fuerteventura",
  "smallHeading": "",
  "images": [
    {
      "file": "fuerteventura-10",
      "alt": "fuerteventura-01",
      "layout": "landscape"
    },
    {
      "file": "fuerteventura-02",
      "alt": "fuerteventura-02",
      "layout": "landscape"
    },
    {
      "file": "fuerteventura-03",
      "alt": "fuerteventura-03",
      "layout": "panoramic"
    },
    {
      "file": "fuerteventura-04",
      "alt": "fuerteventura-04",
      "layout": "landscape"
    },
    {
      "file": "fuerteventura-05",
      "alt": "fuerteventura-05",
      "layout": "landscape"
    },
    {
      "file": "fuerteventura-06",
      "alt": "fuerteventura-06",
      "layout": "landscape"
    },
    {
      "file": "fuerteventura-07",
      "alt": "fuerteventura-07",
      "layout": "portrait"
    },
    {
      "file": "fuerteventura-08",
      "alt": "fuerteventura-08",
      "layout": "landscape"
    },
    {
      "file": "fuerteventura-09",
      "alt": "fuerteventura-09",
      "layout": "landscape"
    },
    {
      "file": "fuerteventura-01",
      "alt": "carpathians-09",
      "layout": "panoramic"
    }
  ]
}
