{
  "name": "scarborough",
  "largeHeading": "Scarborough",
  "smallHeading": "",
  "images": [
    {
      "file": "scarborough-05",
      "alt": "South Bay Roundabout with subway",
      "layout": "portrait"
    },
    {
      "file": "scarborough-02",
      "alt": "Chippy thief",
      "layout": "landscape"
    },
    {
      "file": "scarborough-03",
      "alt": "Scarborough",
      "layout": "landscape"
    },
    {
      "file": "scarborough-04",
      "alt": "South Bay",
      "layout": "landscape"
    },
    {
      "file": "scarborough-01",
      "alt": "Eye protection is for losers",
      "layout": "square"
    }
  ]
}
